findingmodel/__init__.py
findingmodel/__main__.py
findingmodel/abstract_finding_model.py
findingmodel/cli.py
findingmodel/common.py
findingmodel/config.py
findingmodel/contributor.py
findingmodel/create_stub.py
findingmodel/data/.gitignore
findingmodel/data/base_organizations.jsonl
findingmodel/data/base_people.jsonl
findingmodel/finding_info.py
findingmodel/finding_model.py
findingmodel/fm_md_template.py
findingmodel/index.py
findingmodel/index_validation.py
findingmodel/mcp_server.py
findingmodel/protocols.py
findingmodel/py.typed
findingmodel/tools/__init__.py
findingmodel/tools/duckdb_utils.py
findingmodel/tools/index_codes.py
findingmodel-1.0.0.dist-info/WHEEL
findingmodel-1.0.0.dist-info/entry_points.txt
findingmodel-1.0.0.dist-info/METADATA
findingmodel-1.0.0.dist-info/RECORD
