Metadata-Version: 2.4
Name: findingmodel
Version: 1.0.0
Summary: Definition and tools for Open Imaging Finding Models
Keywords: finding model,common data element,medical imaging,data model,radiology
Author: Tarik Alkasab, Vijay Dawal
Author-email: Tarik Alkasab <tarik@alkasab.org>, Vijay Dawal <vijaydawal@microsoft.com>
License-Expression: MIT
Classifier: Programming Language :: Python :: 3
Classifier: Operating System :: OS Independent
Requires-Dist: oidm-common
Requires-Dist: click>=8.1.8
Requires-Dist: duckdb>=1.0
Requires-Dist: jinja2>=3.1.6
Requires-Dist: loguru>=0.7
Requires-Dist: mcp>=1.0.0
Requires-Dist: pydantic[email]>=2.0
Requires-Dist: pydantic-settings>=2.9
Requires-Dist: rich>=13.9.4
Requires-Dist: openai>=1.0 ; extra == 'openai'
Requires-Python: >=3.11
Project-URL: Homepage, https://github.com/openimagingdata/findingmodel
Project-URL: Issues, https://github.com/openimagingdata/findingmodel/issues
Provides-Extra: openai
